pylint_odoo/__init__.py
pylint_odoo/misc.py
pylint_odoo/plugin.py
pylint_odoo/augmentations/__init__.py
pylint_odoo/augmentations/main.py
pylint_odoo/checkers/__init__.py
pylint_odoo/checkers/custom_logging.py
pylint_odoo/checkers/odoo_addons.py
pylint_odoo/checkers/odoo_base_checker.py
pylint_odoo/checkers/vim_comment.py
pylint_odoo-10.0.0.dist-info/METADATA
pylint_odoo-10.0.0.dist-info/WHEEL
pylint_odoo-10.0.0.dist-info/top_level.txt
pylint_odoo-10.0.0.dist-info/RECORD
