Metadata-Version: 2.4
Name: pylint-odoo
Version: 10.0.0
Summary: Pylint plugin for Odoo
Home-page: https://github.com/OCA/pylint-odoo
Author: Odoo Community Association (OCA)
Author-email: support@odoo-community.org
License: APGL3
Classifier: Development Status :: 6 - Mature
Classifier: Environment :: Console
Classifier: Intended Audience :: Developers
Classifier: Intended Audience :: Information Technology
Classifier: License :: OSI Approved :: GNU Affero General Public License v3 or later (AGPLv3+)
Classifier: Operating System :: OS Independent
Classifier: Programming Language :: Python
Classifier: Programming Language :: Python :: 3
Classifier: Programming Language :: Python :: 3 :: Only
Classifier: Programming Language :: Python :: 3.10
Classifier: Programming Language :: Python :: 3.11
Classifier: Programming Language :: Python :: 3.12
Classifier: Programming Language :: Python :: 3.13
Classifier: Programming Language :: Python :: 3.14
Classifier: Topic :: Software Development :: Debuggers
Classifier: Topic :: Software Development :: Quality Assurance
Classifier: Topic :: Software Development :: Testing
Requires-Dist: pylint-plugin-utils==0.9.*
Requires-Dist: pylint==4.0.*
Dynamic: description
Dynamic: requires-dist
